[
	{
		"name": "Guarda Imperial",
		"unitType": "Ranged Gunpowder",
		"uniqueTo": "Republica Imperial",
		"movement": 7,
		"strength": 100,
		"rangedStrength": 36,
		"range": 7,
		"cost": 10,
		"promotions": ["Logistics","Accuracy I","Accuracy II","Accuracy III"],
		"unique": ["May withdraw before melee ([50]%)", "Can see over obstacles", "Invisible to non-adjacent units", "Can see invisible [All] units", "All tiles cost 1 movement", "May travel on Water tiles without embarking", "No movement cost to pillage", "Eliminates combat penalty for attacking across a coast", "May attack when embarked", "Eliminates combat penalty for attacking over a river", "Ranged attacks may be performed over obstacles", "May Paradrop up to [10] tiles from inside friendly territory", "Can perform Air Sweep", "Normal vision when embarked", "May attack when embarked", "Can see over obstacles", "May enter foreign tiles without open borders", "Ranged attacks may be performed over obstacles", "Can enter ice tiles", "[10]% chance to intercept air attacks", "Can move immediately once bought", "Can move after attacking", "Unit will heal every turn, even if it performs an action", "No movement cost to pillage", "All tiles cost 1 movement", "Can pass through impassable tiles","Blast radius [1]", "May capture killed [All] units", "Uncapturable", "[100]% chance to intercept air attacks", "[2] additional attacks per turn", "Invisible to others","Can move after attacking", "Normal vision when embarked", "May attack when embarked", "Can see over obstacles", "May enter foreign tiles without open borders", "Ranged attacks may be performed over obstacles", "Can enter ice tiles", "Can pass through impassable tiles"]
		
	{
		"name": "Imperial Droids",
		"unitType": "Ranged Gunpowder",
		"uniqueTo": "Republica Imperial",
		"movement": 7,
		"strength": 300,
		"rangedStrength": 46,
		"range": 10,
		"cost": 10,
		"promotions": ["Logistics","Accuracy I","Accuracy II","Accuracy III"],
		"unique": ["May withdraw before melee ([50]%)", "Can see over obstacles", "Invisible to non-adjacent units", "Can see invisible [All] units", "All tiles cost 1 movement", "May travel on Water tiles without embarking", "No movement cost to pillage", "Eliminates combat penalty for attacking across a coast", "May attack when embarked", "Eliminates combat penalty for attacking over a river", "Ranged attacks may be performed over obstacles", "May Paradrop up to [10] tiles from inside friendly territory", "Can perform Air Sweep", "Normal vision when embarked", "May attack when embarked", "Can see over obstacles", "May enter foreign tiles without open borders", "Ranged attacks may be performed over obstacles", "Can enter ice tiles", "[10]% chance to intercept air attacks", "Can move immediately once bought", "Can move after attacking", "Unit will heal every turn, even if it performs an action", "No movement cost to pillage", "All tiles cost 1 movement", "Can pass through impassable tiles","Blast radius [1]", "May capture killed [All] units", "Uncapturable", "[100]% chance to intercept air attacks", "[2] additional attacks per turn", "Invisible to others","Can move after attacking", "Normal vision when embarked", "May attack when embarked", "Can see over obstacles", "May enter foreign tiles without open borders", "Ranged attacks may be performed over obstacles", "Can enter ice tiles", "Can pass through impassable tiles"]
	}
	{
		"name": "jedi",
		"unitType": "Mounted",
		"uniqueTo": "Republica Imperial",
		"movement": 7,
		"strength": 500,
		"rangedStrength": 56,
		"range": 15,
		"cost": 10,
		"promotions": ["Logistics","Accuracy I","Accuracy II","Accuracy III"],
		"unique": ["May withdraw before melee ([50]%)", "Can see over obstacles", "Invisible to non-adjacent units", "Can see invisible [All] units", "All tiles cost 1 movement", "May travel on Water tiles without embarking", "No movement cost to pillage", "Eliminates combat penalty for attacking across a coast", "May attack when embarked", "Eliminates combat penalty for attacking over a river", "Ranged attacks may be performed over obstacles", "May Paradrop up to [10] tiles from inside friendly territory", "Can perform Air Sweep", "Normal vision when embarked", "May attack when embarked", "Can see over obstacles", "May enter foreign tiles without open borders", "Ranged attacks may be performed over obstacles", "Can enter ice tiles", "[10]% chance to intercept air attacks", "Can move immediately once bought", "Can move after attacking", "Unit will heal every turn, even if it performs an action", "No movement cost to pillage", "All tiles cost 1 movement", "Can pass through impassable tiles","Blast radius [1]", "May capture killed [All] units", "Uncapturable", "[100]% chance to intercept air attacks", "[2] additional attacks per turn", "Invisible to others","Can move after attacking", "Normal vision when embarked", "May attack when embarked", "Can see over obstacles", "May enter foreign tiles without open borders", "Ranged attacks may be performed over obstacles", "Can enter ice tiles", "Can pass through impassable tiles"]
	}
	{
		"name": "Sith",
		"unitType": "Mounted",
		"uniqueTo": "Republica Imperial",
		"movement": 7,
		"strength": 500,
		"rangedStrength": 56,
		"range": 15,
		"cost": 10,
		"promotions": ["Logistics","Accuracy I","Accuracy II","Accuracy III"],
		"unique": ["May withdraw before melee ([50]%)", "Can see over obstacles", "Invisible to non-adjacent units", "Can see invisible [All] units", "All tiles cost 1 movement", "May travel on Water tiles without embarking", "No movement cost to pillage", "Eliminates combat penalty for attacking across a coast", "May attack when embarked", "Eliminates combat penalty for attacking over a river", "Ranged attacks may be performed over obstacles", "May Paradrop up to [10] tiles from inside friendly territory", "Can perform Air Sweep", "Normal vision when embarked", "May attack when embarked", "Can see over obstacles", "May enter foreign tiles without open borders", "Ranged attacks may be performed over obstacles", "Can enter ice tiles", "[10]% chance to intercept air attacks", "Can move immediately once bought", "Can move after attacking", "Unit will heal every turn, even if it performs an action", "No movement cost to pillage", "All tiles cost 1 movement", "Can pass through impassable tiles","Blast radius [1]", "May capture killed [All] units", "Uncapturable", "[100]% chance to intercept air attacks", "[2] additional attacks per turn", "Invisible to others","Can move after attacking", "Normal vision when embarked", "May attack when embarked", "Can see over obstacles", "May enter foreign tiles without open borders", "Ranged attacks may be performed over obstacles", "Can enter ice tiles", "Can pass through impassable tiles"]
	}
{ 
  "name": "Super Cheat Worker", 
  "uniqueTo": "Republica Imperial", 
  "unitType": "Civilian", 
  "movement": 5,
  "attackSound": "arrow",
  "uniques": ["Can build [Land] improvements on tiles", "Can build [Water] improvements on tiles", "Never appears as a Barbarian unit", "Can move after attacking", "Can move immediately once bought", "May create improvements on water resources", "Uncapturable", "[5] Sight" ], 
  "cost": 10 
}
{ "name": "Super Cheat Settler", 
  "uniqueTo": "Republica Imperial", 
  "unitType": "Civilian", 
  "movement": 5, 
  "attackSound": "arrow", 
  "uniques": ["Founds a new city", "Never appears as a Barbarian unit", "Can move after attacking", "Can move immediately once bought", "Uncapturable", "[5] Sight" ], 
  "cost": 10 
}
{ "name": "Primeiro Comando da Aliança", 
  "uniqueTo": "Republica Imperial", 
  "unitType": "Ranged Gunpowder", 
  "movement": 5,
  "strength": 400, 
  "rangedStrength": 100,
  "attackSound": "arrow", 
  "uniques": ["Never appears as a Barbarian unit", "Can move after attacking", "Can move immediately once bought", "Uncapturable", "[2] additional attacks per turn", "[5] Sight", "[5] Range", "May withdraw before melee ([50]%)", "Can move after attacking", "Can see over obstacles", "Invisible to non-adjacent units", "Can see invisible [All] units", "All tiles cost 1 movement", "May travel on Water tiles without embarking", "No movement cost to pillage", "Eliminates combat penalty for attacking across a coast", "May attack when embarked", "Eliminates combat penalty for attacking over a river", "Ranged attacks may be performed over obstacles" ], 
  "cost": 10 
}
{ "name": "Primeiro Comando Imperial", 
  "uniqueTo": "Republica Imperial", 
  "unitType": "Ranged Gunpowder", 
  "movement": 5,
  "strength": 400,  
  "attackSound": "arrow", 
  "uniques": ["Never appears as a Barbarian unit", "Can move after attacking", "Can move immediately once bought", "Uncapturable", "[2] additional attacks per turn", "[5] Sight", "[5] Range", "May withdraw before melee ([50]%)", "Can move after attacking", "Can see over obstacles", "Invisible to non-adjacent units", "Can see invisible [All] units", "All tiles cost 1 movement", "May travel on Water tiles without embarking", "No movement cost to pillage", "Eliminates combat penalty for attacking across a coast", "May attack when embarked", "Eliminates combat penalty for attacking over a river", "Ranged attacks may be performed over obstacles" ], 
  "cost": 10 
}
	
]
